rxdpy/__init__.py
rxdpy/aes_cbc.py
rxdpy/base58.py
rxdpy/constants.py
rxdpy/crypto/__init__.py
rxdpy/curve.py
rxdpy/fee_model.py
rxdpy/fee_models/__init__.py
rxdpy/fee_models/satoshis_per_kilobyte.py
rxdpy/hash.py
rxdpy/hd/__init__.py
rxdpy/hd/bip32.py
rxdpy/hd/bip39.py
rxdpy/hd/bip44.py
rxdpy/hd/wordlist/chinese_simplified.txt
rxdpy/hd/wordlist/english.txt
rxdpy/keys.py
rxdpy/merkle_path.py
rxdpy/script/__init__.py
rxdpy/script/script.py
rxdpy/script/spend.py
rxdpy/script/type.py
rxdpy/script/unlocking_template.py
rxdpy/transaction/__init__.py
rxdpy/transaction/transaction.py
rxdpy/transaction/transaction_input.py
rxdpy/transaction/transaction_output.py
rxdpy/transaction/transaction_preimage.py
rxdpy/utils.py
rxdpy-0.1.0.dist-info/LICENSE
rxdpy-0.1.0.dist-info/METADATA
rxdpy-0.1.0.dist-info/WHEEL
rxdpy-0.1.0.dist-info/RECORD
